README.md
setup.cfg
setup.py
BLUvo.egg-info/PKG-INFO
BLUvo.egg-info/SOURCES.txt
BLUvo.egg-info/dependency_links.txt
BLUvo.egg-info/requires.txt
BLUvo.egg-info/top_level.txt
bluvo/__init__.py
bluvo/api/__init__.py
bluvo/api/bluvo_interface.py
bluvo/api/ca_hyundai_implementation.py
bluvo/api/ca_implementation.py
bluvo/api/ca_kia_implementation.py
bluvo/api/eu_hyundai_implementation.py
bluvo/api/eu_implementation.py
bluvo/api/eu_kia_implementation.py
bluvo/api/us_hyundai_implementation.py
bluvo/api/us_kia_implementation.py
bluvo/api/helpers/__init__.py
bluvo/api/helpers/constants.py
bluvo/api/helpers/dict_helpers.py
bluvo/api/helpers/either.py
bluvo/api/helpers/exceptions.py
bluvo/api/helpers/temperature_helpers.py
bluvo/api/vehicles/__init__.py
bluvo/api/vehicles/ca_vehicle.py