Metadata-Version: 1.1
Name: BLUvo
Version: 0.9
Summary: API Wrapper for the Bluelink/Uvo service
Home-page: https://github.com/wcomartin/bluvo
Author: William Comartin
Author-email: williamcomartin@gmail.com
License: MIT
Download-URL: https://github.com/wcomartin/bluvo/archive/v_0.9.tar.gz
Keywords: Kia,Uvo,Api,bluelink
Platform: UNKNOWN
Classifier: Development Status :: 3 - Alpha
Classifier: Intended Audience :: Developers
Classifier: Topic :: Software Development :: Build Tools
Classifier: License :: OSI Approved :: MIT License
Classifier: Programming Language :: Python :: 3
Classifier: Programming Language :: Python :: 3.4
Classifier: Programming Language :: Python :: 3.5
Classifier: Programming Language :: Python :: 3.6
